setup.py
dmkjlib/__init__.py
dmkjlib/prcss.py
dmkjlib/tks.py
dmkjlib.egg-info/PKG-INFO
dmkjlib.egg-info/SOURCES.txt
dmkjlib.egg-info/dependency_links.txt
dmkjlib.egg-info/top_level.txt